llmbridge/__init__.py
llmbridge/base.py
llmbridge/cache.py
llmbridge/cli.py
llmbridge/config.py
llmbridge/db.py
llmbridge/db_sqlite.py
llmbridge/file_utils.py
llmbridge/formatter.py
llmbridge/schemas.py
llmbridge/service.py
llmbridge/service_sqlite.py
llmbridge/api/__init__.py
llmbridge/api/service.py
llmbridge/api/types.py
llmbridge/interfaces/__init__.py
llmbridge/interfaces/usage_tracker.py
llmbridge/migrations/001_llm_schema.sql
llmbridge/model_extraction/__init__.py
llmbridge/model_extraction/extract_models.py
llmbridge/model_extraction/json_generator.py
llmbridge/model_extraction/model_curator.py
llmbridge/model_extraction/pdf_parser.py
llmbridge/model_refresh/__init__.py
llmbridge/model_refresh/async_database_updater.py
llmbridge/model_refresh/async_refresh_manager.py
llmbridge/model_refresh/backup_manager.py
llmbridge/model_refresh/complete_refresh_manager.py
llmbridge/model_refresh/database_updater.py
llmbridge/model_refresh/json_model_loader.py
llmbridge/model_refresh/json_refresh_manager.py
llmbridge/model_refresh/model_comparator.py
llmbridge/model_refresh/model_filter.py
llmbridge/model_refresh/models.py
llmbridge/model_refresh/refresh_manager.py
llmbridge/pricing/__init__.py
llmbridge/pricing/anthropic_pricing.py
llmbridge/pricing/google_pricing.py
llmbridge/pricing/llm_processor.py
llmbridge/pricing/openai_pricing.py
llmbridge/pricing/scraper_base.py
llmbridge/providers/__init__.py
llmbridge/providers/anthropic_api.py
llmbridge/providers/google_api.py
llmbridge/providers/ollama_api.py
llmbridge/providers/openai_api.py
llmbridge_py-0.2.3.dist-info/METADATA
llmbridge_py-0.2.3.dist-info/WHEEL
llmbridge_py-0.2.3.dist-info/entry_points.txt
llmbridge_py-0.2.3.dist-info/licenses/LICENSE
llmbridge_py-0.2.3.dist-info/RECORD
