Metadata-Version: 2.4
Name: llmbridge-py
Version: 0.2.3
Summary: Unified Python interface for OpenAI, Anthropic, Google, and Ollama LLMs with optional model registry and usage tracking - deprecated
Project-URL: Homepage, https://juanreyero.com/open/llmbridge/
Project-URL: Documentation, https://github.com/juanre/llmbridge
Project-URL: Repository, https://github.com/juanre/llmbridge
Project-URL: Issues, https://github.com/juanre/llmbridge/issues
Author-email: Juan Reyero <juan@juanreyero.com>
Maintainer-email: Juan Reyero <juan@juanreyero.com>
License: MIT
License-File: LICENSE
Keywords: ai,anthropic,api,claude,gemini,gpt,llm,ollama,openai
Classifier: Development Status :: 4 - Beta
Classifier: Intended Audience :: Developers
Classifier: License :: OSI Approved :: MIT License
Classifier: Programming Language :: Python :: 3
Classifier: Programming Language :: Python :: 3.10
Classifier: Programming Language :: Python :: 3.11
Classifier: Programming Language :: Python :: 3.12
Classifier: Programming Language :: Python :: 3.13
Classifier: Topic :: Scientific/Engineering :: Artificial Intelligence
Classifier: Topic :: Software Development :: Libraries :: Python Modules
Requires-Python: >=3.10
Requires-Dist: aiohttp>=3.8.0
Requires-Dist: aiosqlite>=0.19.0
Requires-Dist: anthropic>=0.18.0
Requires-Dist: beautifulsoup4>=4.12.0
Requires-Dist: google-genai>=0.1.0
Requires-Dist: httpx>=0.24.0
Requires-Dist: ollama>=0.4.0
Requires-Dist: openai>=1.0.0
Requires-Dist: pgdbm>=0.1.0
Requires-Dist: psycopg2-binary>=2.9.0
Requires-Dist: pydantic>=2.0.0
Requires-Dist: python-dotenv>=1.0.0
Provides-Extra: dev
Requires-Dist: black>=23.0; extra == 'dev'
Requires-Dist: fastapi>=0.100.0; extra == 'dev'
Requires-Dist: isort>=5.0; extra == 'dev'
Requires-Dist: pillow>=10.0.0; extra == 'dev'
Requires-Dist: pyright>=1.1; extra == 'dev'
Requires-Dist: pytest-asyncio>=0.21; extra == 'dev'
Requires-Dist: pytest-mock>=3.10; extra == 'dev'
Requires-Dist: pytest>=7.0; extra == 'dev'
Requires-Dist: uvicorn>=0.23.0; extra == 'dev'
Provides-Extra: postgres
Requires-Dist: pgdbm>=0.1.0; extra == 'postgres'
